nostr_protocol/__init__.py
nostr_protocol/nostr_ffi.dll
nostr_protocol/nostr_ffi.py
nostr_protocol-0.35.0.dist-info/LICENSE
nostr_protocol-0.35.0.dist-info/METADATA
nostr_protocol-0.35.0.dist-info/WHEEL
nostr_protocol-0.35.0.dist-info/top_level.txt
nostr_protocol-0.35.0.dist-info/RECORD
