Metadata-Version: 2.1
Name: nostr-protocol
Version: 0.35.0
Summary: Nostr protocol implementation
Home-page: https://github.com/rust-nostr/nostr
Author: Yuki Kishimoto <yukikishimoto@protonmail.com>
License: MIT
License-File: LICENSE
